.gitignore
CHANGELOG.md
CONTRIBUTING.md
LICENSE.txt
Makefile
README.md
RELEASE.md
environment.yml
pyproject.toml
requirements-dev.txt
requirements.txt
setup.cfg
setup.py
.github/workflows/test.yml
pelican_jupyter/__init__.py
pelican_jupyter/_generated_version.py
pelican_jupyter/core.py
pelican_jupyter/liquid.py
pelican_jupyter/markup.py
pelican_jupyter.egg-info/PKG-INFO
pelican_jupyter.egg-info/SOURCES.txt
pelican_jupyter.egg-info/dependency_links.txt
pelican_jupyter.egg-info/not-zip-safe
pelican_jupyter.egg-info/requires.txt
pelican_jupyter.egg-info/top_level.txt
pelican_jupyter/tests/__init__.py
pelican_jupyter/tests/test_base_usage.py
pelican_jupyter/tests/test_import.py
pelican_jupyter/tests/pelican/liquid/pelicanconf.py
pelican_jupyter/tests/pelican/liquid/content/liquid-tag.ipynb
pelican_jupyter/tests/pelican/liquid/content/liquid-tag.md
pelican_jupyter/tests/pelican/markup-incell/pelicanconf.py
pelican_jupyter/tests/pelican/markup-incell/content/md-info-in-cell.ipynb
pelican_jupyter/tests/pelican/markup-nbdata/pelicanconf.py
pelican_jupyter/tests/pelican/markup-nbdata/content/nbdata-file.ipynb
pelican_jupyter/tests/pelican/markup-nbdata/content/nbdata-file.nbdata
pelican_jupyter/vendor/__init__.py
pelican_jupyter/vendor/liquid_tags/__init__.py
pelican_jupyter/vendor/liquid_tags/liquid_tags.py
pelican_jupyter/vendor/liquid_tags/mdx_liquid_tags.py