Metadata-Version: 2.1
Name: pelican-jupyter
Version: 0.10.1
Summary: Pelican plugin for blogging with Jupyter/IPython Notebooks
Home-page: https://github.com/danielfrg/pelican-jupyter
Maintainer: Daniel Rodriguez
Maintainer-email: daniel@danielfrg.com
License: Apache License, Version 2.0
Platform: UNKNOWN
Classifier: License :: OSI Approved :: Apache Software License
Classifier: Programming Language :: Python :: 3.7
Classifier: Programming Language :: Python :: 3.8
Classifier: Programming Language :: Python :: 3.9
Requires-Python: >=3.7
Provides-Extra: test
Provides-Extra: dev
